{"updated":"2026-06-11T12:53:12.615Z","source":"api-football.com","matches":[{"stage":"GROUP_STAGE","utcDate":"2026-06-11T19:00:00+00:00","home":"Mexico","away":"South Africa","status":"NS"},{"stage":"GROUP_STAGE","utcDate":"2026-06-12T02:00:00+00:00","home":"South Korea","away":"Czech Republic","status":"NS"},{"stage":"GROUP_STAGE","utcDate":"2026-06-12T19:00:00+00:00","home":"Canada","away":"Bosnia & Herzegovina","status":"NS"},{"stage":"GROUP_STAGE","utcDate":"2026-06-13T01:00:00+00:00","home":"USA","away":"Paraguay","status":"NS"},{"stage":"GROUP_STAGE","utcDate":"2026-06-13T19:00:00+00:00","home":"Qatar","away":"Switzerland","status":"NS"},{"stage":"GROUP_STAGE","utcDate":"2026-06-13T22:00:00+00:00","home":"Brazil","away":"Morocco","status":"NS"},{"stage":"GROUP_STAGE","utcDate":"2026-06-14T01:00:00+00:00","home":"Haiti","away":"Scotland","status":"NS"},{"stage":"GROUP_STAGE","utcDate":"2026-06-14T04:00:00+00:00","home":"Australia","away":"Türkiye","status":"NS"},{"stage":"GROUP_STAGE","utcDate":"2026-06-14T17:00:00+00:00","home":"Germany","away":"Curaçao","status":"NS"},{"stage":"GROUP_STAGE","utcDate":"2026-06-14T20:00:00+00:00","home":"Netherlands","away":"Japan","status":"NS"},{"stage":"GROUP_STAGE","utcDate":"2026-06-14T23:00:00+00:00","home":"Ivory Coast","away":"Ecuador","status":"NS"},{"stage":"GROUP_STAGE","utcDate":"2026-06-15T02:00:00+00:00","home":"Sweden","away":"Tunisia","status":"NS"},{"stage":"GROUP_STAGE","utcDate":"2026-06-15T16:00:00+00:00","home":"Spain","away":"Cape Verde Islands","status":"NS"},{"stage":"GROUP_STAGE","utcDate":"2026-06-15T19:00:00+00:00","home":"Belgium","away":"Egypt","status":"NS"},{"stage":"GROUP_STAGE","utcDate":"2026-06-15T22:00:00+00:00","home":"Saudi Arabia","away":"Uruguay","status":"NS"},{"stage":"GROUP_STAGE","utcDate":"2026-06-16T01:00:00+00:00","home":"Iran","away":"New Zealand","status":"NS"},{"stage":"GROUP_STAGE","utcDate":"2026-06-16T19:00:00+00:00","home":"France","away":"Senegal","status":"NS"},{"stage":"GROUP_STAGE","utcDate":"2026-06-16T22:00:00+00:00","home":"Iraq","away":"Norway","status":"NS"},{"stage":"GROUP_STAGE","utcDate":"2026-06-17T01:00:00+00:00","home":"Argentina","away":"Algeria","status":"NS"},{"stage":"GROUP_STAGE","utcDate":"2026-06-17T04:00:00+00:00","home":"Austria","away":"Jordan","status":"NS"},{"stage":"GROUP_STAGE","utcDate":"2026-06-17T17:00:00+00:00","home":"Portugal","away":"Congo DR","status":"NS"},{"stage":"GROUP_STAGE","utcDate":"2026-06-17T20:00:00+00:00","home":"England","away":"Croatia","status":"NS"},{"stage":"GROUP_STAGE","utcDate":"2026-06-17T23:00:00+00:00","home":"Ghana","away":"Panama","status":"NS"},{"stage":"GROUP_STAGE","utcDate":"2026-06-18T02:00:00+00:00","home":"Uzbekistan","away":"Colombia","status":"NS"},{"stage":"GROUP_STAGE","utcDate":"2026-06-18T16:00:00+00:00","home":"Czech Republic","away":"South Africa","status":"NS"},{"stage":"GROUP_STAGE","utcDate":"2026-06-18T19:00:00+00:00","home":"Switzerland","away":"Bosnia & Herzegovina","status":"NS"},{"stage":"GROUP_STAGE","utcDate":"2026-06-18T22:00:00+00:00","home":"Canada","away":"Qatar","status":"NS"},{"stage":"GROUP_STAGE","utcDate":"2026-06-19T01:00:00+00:00","home":"Mexico","away":"South Korea","status":"NS"},{"stage":"GROUP_STAGE","utcDate":"2026-06-19T19:00:00+00:00","home":"USA","away":"Australia","status":"NS"},{"stage":"GROUP_STAGE","utcDate":"2026-06-19T22:00:00+00:00","home":"Scotland","away":"Morocco","status":"NS"},{"stage":"GROUP_STAGE","utcDate":"2026-06-20T00:30:00+00:00","home":"Brazil","away":"Haiti","status":"NS"},{"stage":"GROUP_STAGE","utcDate":"2026-06-20T03:00:00+00:00","home":"Türkiye","away":"Paraguay","status":"NS"},{"stage":"GROUP_STAGE","utcDate":"2026-06-20T17:00:00+00:00","home":"Netherlands","away":"Sweden","status":"NS"},{"stage":"GROUP_STAGE","utcDate":"2026-06-20T20:00:00+00:00","home":"Germany","away":"Ivory Coast","status":"NS"},{"stage":"GROUP_STAGE","utcDate":"2026-06-21T00:00:00+00:00","home":"Ecuador","away":"Curaçao","status":"NS"},{"stage":"GROUP_STAGE","utcDate":"2026-06-21T04:00:00+00:00","home":"Tunisia","away":"Japan","status":"NS"},{"stage":"GROUP_STAGE","utcDate":"2026-06-21T16:00:00+00:00","home":"Spain","away":"Saudi Arabia","status":"NS"},{"stage":"GROUP_STAGE","utcDate":"2026-06-21T19:00:00+00:00","home":"Belgium","away":"Iran","status":"NS"},{"stage":"GROUP_STAGE","utcDate":"2026-06-21T22:00:00+00:00","home":"Uruguay","away":"Cape Verde Islands","status":"NS"},{"stage":"GROUP_STAGE","utcDate":"2026-06-22T01:00:00+00:00","home":"New Zealand","away":"Egypt","status":"NS"},{"stage":"GROUP_STAGE","utcDate":"2026-06-22T17:00:00+00:00","home":"Argentina","away":"Austria","status":"NS"},{"stage":"GROUP_STAGE","utcDate":"2026-06-22T21:00:00+00:00","home":"France","away":"Iraq","status":"NS"},{"stage":"GROUP_STAGE","utcDate":"2026-06-23T00:00:00+00:00","home":"Norway","away":"Senegal","status":"NS"},{"stage":"GROUP_STAGE","utcDate":"2026-06-23T03:00:00+00:00","home":"Jordan","away":"Algeria","status":"NS"},{"stage":"GROUP_STAGE","utcDate":"2026-06-23T17:00:00+00:00","home":"Portugal","away":"Uzbekistan","status":"NS"},{"stage":"GROUP_STAGE","utcDate":"2026-06-23T20:00:00+00:00","home":"England","away":"Ghana","status":"NS"},{"stage":"GROUP_STAGE","utcDate":"2026-06-23T23:00:00+00:00","home":"Panama","away":"Croatia","status":"NS"},{"stage":"GROUP_STAGE","utcDate":"2026-06-24T02:00:00+00:00","home":"Colombia","away":"Congo DR","status":"NS"},{"stage":"GROUP_STAGE","utcDate":"2026-06-24T19:00:00+00:00","home":"Switzerland","away":"Canada","status":"NS"},{"stage":"GROUP_STAGE","utcDate":"2026-06-24T19:00:00+00:00","home":"Bosnia & Herzegovina","away":"Qatar","status":"NS"},{"stage":"GROUP_STAGE","utcDate":"2026-06-24T22:00:00+00:00","home":"Morocco","away":"Haiti","status":"NS"},{"stage":"GROUP_STAGE","utcDate":"2026-06-24T22:00:00+00:00","home":"Scotland","away":"Brazil","status":"NS"},{"stage":"GROUP_STAGE","utcDate":"2026-06-25T01:00:00+00:00","home":"Czech Republic","away":"Mexico","status":"NS"},{"stage":"GROUP_STAGE","utcDate":"2026-06-25T01:00:00+00:00","home":"South Africa","away":"South Korea","status":"NS"},{"stage":"GROUP_STAGE","utcDate":"2026-06-25T20:00:00+00:00","home":"Ecuador","away":"Germany","status":"NS"},{"stage":"GROUP_STAGE","utcDate":"2026-06-25T20:00:00+00:00","home":"Curaçao","away":"Ivory Coast","status":"NS"},{"stage":"GROUP_STAGE","utcDate":"2026-06-25T23:00:00+00:00","home":"Japan","away":"Sweden","status":"NS"},{"stage":"GROUP_STAGE","utcDate":"2026-06-25T23:00:00+00:00","home":"Tunisia","away":"Netherlands","status":"NS"},{"stage":"GROUP_STAGE","utcDate":"2026-06-26T02:00:00+00:00","home":"Türkiye","away":"USA","status":"NS"},{"stage":"GROUP_STAGE","utcDate":"2026-06-26T02:00:00+00:00","home":"Paraguay","away":"Australia","status":"NS"},{"stage":"GROUP_STAGE","utcDate":"2026-06-26T19:00:00+00:00","home":"Senegal","away":"Iraq","status":"NS"},{"stage":"GROUP_STAGE","utcDate":"2026-06-26T19:00:00+00:00","home":"Norway","away":"France","status":"NS"},{"stage":"GROUP_STAGE","utcDate":"2026-06-27T00:00:00+00:00","home":"Uruguay","away":"Spain","status":"NS"},{"stage":"GROUP_STAGE","utcDate":"2026-06-27T00:00:00+00:00","home":"Cape Verde Islands","away":"Saudi Arabia","status":"NS"},{"stage":"GROUP_STAGE","utcDate":"2026-06-27T03:00:00+00:00","home":"Egypt","away":"Iran","status":"NS"},{"stage":"GROUP_STAGE","utcDate":"2026-06-27T03:00:00+00:00","home":"New Zealand","away":"Belgium","status":"NS"},{"stage":"GROUP_STAGE","utcDate":"2026-06-27T21:00:00+00:00","home":"Croatia","away":"Ghana","status":"NS"},{"stage":"GROUP_STAGE","utcDate":"2026-06-27T21:00:00+00:00","home":"Panama","away":"England","status":"NS"},{"stage":"GROUP_STAGE","utcDate":"2026-06-27T23:30:00+00:00","home":"Colombia","away":"Portugal","status":"NS"},{"stage":"GROUP_STAGE","utcDate":"2026-06-27T23:30:00+00:00","home":"Congo DR","away":"Uzbekistan","status":"NS"},{"stage":"GROUP_STAGE","utcDate":"2026-06-28T02:00:00+00:00","home":"Algeria","away":"Austria","status":"NS"},{"stage":"GROUP_STAGE","utcDate":"2026-06-28T02:00:00+00:00","home":"Jordan","away":"Argentina","status":"NS"}],"standings":{"A":[{"team":"Mexico","p":0,"w":0,"d":0,"l":0,"gf":0,"ga":0,"gd":0,"pts":0},{"team":"South Africa","p":0,"w":0,"d":0,"l":0,"gf":0,"ga":0,"gd":0,"pts":0},{"team":"South Korea","p":0,"w":0,"d":0,"l":0,"gf":0,"ga":0,"gd":0,"pts":0},{"team":"Czech Republic","p":0,"w":0,"d":0,"l":0,"gf":0,"ga":0,"gd":0,"pts":0}],"B":[{"team":"Canada","p":0,"w":0,"d":0,"l":0,"gf":0,"ga":0,"gd":0,"pts":0},{"team":"Bosnia & Herzegovina","p":0,"w":0,"d":0,"l":0,"gf":0,"ga":0,"gd":0,"pts":0},{"team":"Qatar","p":0,"w":0,"d":0,"l":0,"gf":0,"ga":0,"gd":0,"pts":0},{"team":"Switzerland","p":0,"w":0,"d":0,"l":0,"gf":0,"ga":0,"gd":0,"pts":0}],"C":[{"team":"Brazil","p":0,"w":0,"d":0,"l":0,"gf":0,"ga":0,"gd":0,"pts":0},{"team":"Morocco","p":0,"w":0,"d":0,"l":0,"gf":0,"ga":0,"gd":0,"pts":0},{"team":"Haiti","p":0,"w":0,"d":0,"l":0,"gf":0,"ga":0,"gd":0,"pts":0},{"team":"Scotland","p":0,"w":0,"d":0,"l":0,"gf":0,"ga":0,"gd":0,"pts":0}],"D":[{"team":"USA","p":0,"w":0,"d":0,"l":0,"gf":0,"ga":0,"gd":0,"pts":0},{"team":"Paraguay","p":0,"w":0,"d":0,"l":0,"gf":0,"ga":0,"gd":0,"pts":0},{"team":"Australia","p":0,"w":0,"d":0,"l":0,"gf":0,"ga":0,"gd":0,"pts":0},{"team":"Türkiye","p":0,"w":0,"d":0,"l":0,"gf":0,"ga":0,"gd":0,"pts":0}],"E":[{"team":"Germany","p":0,"w":0,"d":0,"l":0,"gf":0,"ga":0,"gd":0,"pts":0},{"team":"Curaçao","p":0,"w":0,"d":0,"l":0,"gf":0,"ga":0,"gd":0,"pts":0},{"team":"Ivory Coast","p":0,"w":0,"d":0,"l":0,"gf":0,"ga":0,"gd":0,"pts":0},{"team":"Ecuador","p":0,"w":0,"d":0,"l":0,"gf":0,"ga":0,"gd":0,"pts":0}],"F":[{"team":"Netherlands","p":0,"w":0,"d":0,"l":0,"gf":0,"ga":0,"gd":0,"pts":0},{"team":"Japan","p":0,"w":0,"d":0,"l":0,"gf":0,"ga":0,"gd":0,"pts":0},{"team":"Sweden","p":0,"w":0,"d":0,"l":0,"gf":0,"ga":0,"gd":0,"pts":0},{"team":"Tunisia","p":0,"w":0,"d":0,"l":0,"gf":0,"ga":0,"gd":0,"pts":0}],"G":[{"team":"Belgium","p":0,"w":0,"d":0,"l":0,"gf":0,"ga":0,"gd":0,"pts":0},{"team":"Egypt","p":0,"w":0,"d":0,"l":0,"gf":0,"ga":0,"gd":0,"pts":0},{"team":"Iran","p":0,"w":0,"d":0,"l":0,"gf":0,"ga":0,"gd":0,"pts":0},{"team":"New Zealand","p":0,"w":0,"d":0,"l":0,"gf":0,"ga":0,"gd":0,"pts":0}],"H":[{"team":"Spain","p":0,"w":0,"d":0,"l":0,"gf":0,"ga":0,"gd":0,"pts":0},{"team":"Cape Verde Islands","p":0,"w":0,"d":0,"l":0,"gf":0,"ga":0,"gd":0,"pts":0},{"team":"Saudi Arabia","p":0,"w":0,"d":0,"l":0,"gf":0,"ga":0,"gd":0,"pts":0},{"team":"Uruguay","p":0,"w":0,"d":0,"l":0,"gf":0,"ga":0,"gd":0,"pts":0}],"I":[{"team":"France","p":0,"w":0,"d":0,"l":0,"gf":0,"ga":0,"gd":0,"pts":0},{"team":"Senegal","p":0,"w":0,"d":0,"l":0,"gf":0,"ga":0,"gd":0,"pts":0},{"team":"Iraq","p":0,"w":0,"d":0,"l":0,"gf":0,"ga":0,"gd":0,"pts":0},{"team":"Norway","p":0,"w":0,"d":0,"l":0,"gf":0,"ga":0,"gd":0,"pts":0}],"J":[{"team":"Argentina","p":0,"w":0,"d":0,"l":0,"gf":0,"ga":0,"gd":0,"pts":0},{"team":"Algeria","p":0,"w":0,"d":0,"l":0,"gf":0,"ga":0,"gd":0,"pts":0},{"team":"Austria","p":0,"w":0,"d":0,"l":0,"gf":0,"ga":0,"gd":0,"pts":0},{"team":"Jordan","p":0,"w":0,"d":0,"l":0,"gf":0,"ga":0,"gd":0,"pts":0}],"K":[{"team":"Portugal","p":0,"w":0,"d":0,"l":0,"gf":0,"ga":0,"gd":0,"pts":0},{"team":"Congo DR","p":0,"w":0,"d":0,"l":0,"gf":0,"ga":0,"gd":0,"pts":0},{"team":"Uzbekistan","p":0,"w":0,"d":0,"l":0,"gf":0,"ga":0,"gd":0,"pts":0},{"team":"Colombia","p":0,"w":0,"d":0,"l":0,"gf":0,"ga":0,"gd":0,"pts":0}],"L":[{"team":"England","p":0,"w":0,"d":0,"l":0,"gf":0,"ga":0,"gd":0,"pts":0},{"team":"Croatia","p":0,"w":0,"d":0,"l":0,"gf":0,"ga":0,"gd":0,"pts":0},{"team":"Ghana","p":0,"w":0,"d":0,"l":0,"gf":0,"ga":0,"gd":0,"pts":0},{"team":"Panama","p":0,"w":0,"d":0,"l":0,"gf":0,"ga":0,"gd":0,"pts":0}],"Ranking of third-placed teams":[{"team":"South Korea","p":0,"w":0,"d":0,"l":0,"gf":0,"ga":0,"gd":0,"pts":0},{"team":"Qatar","p":0,"w":0,"d":0,"l":0,"gf":0,"ga":0,"gd":0,"pts":0},{"team":"Haiti","p":0,"w":0,"d":0,"l":0,"gf":0,"ga":0,"gd":0,"pts":0},{"team":"Australia","p":0,"w":0,"d":0,"l":0,"gf":0,"ga":0,"gd":0,"pts":0},{"team":"Ivory Coast","p":0,"w":0,"d":0,"l":0,"gf":0,"ga":0,"gd":0,"pts":0},{"team":"Sweden","p":0,"w":0,"d":0,"l":0,"gf":0,"ga":0,"gd":0,"pts":0},{"team":"Iran","p":0,"w":0,"d":0,"l":0,"gf":0,"ga":0,"gd":0,"pts":0},{"team":"Saudi Arabia","p":0,"w":0,"d":0,"l":0,"gf":0,"ga":0,"gd":0,"pts":0},{"team":"Iraq","p":0,"w":0,"d":0,"l":0,"gf":0,"ga":0,"gd":0,"pts":0},{"team":"Austria","p":0,"w":0,"d":0,"l":0,"gf":0,"ga":0,"gd":0,"pts":0},{"team":"Uzbekistan","p":0,"w":0,"d":0,"l":0,"gf":0,"ga":0,"gd":0,"pts":0},{"team":"Ghana","p":0,"w":0,"d":0,"l":0,"gf":0,"ga":0,"gd":0,"pts":0}]}}